lss/__init__.py
lss/cli.py
lss/parsers.py
lss/utils.py
layouts_segmentation_simplifier-0.0.2.dist-info/METADATA
layouts_segmentation_simplifier-0.0.2.dist-info/WHEEL
layouts_segmentation_simplifier-0.0.2.dist-info/entry_points.txt
layouts_segmentation_simplifier-0.0.2.dist-info/top_level.txt
layouts_segmentation_simplifier-0.0.2.dist-info/RECORD
