Metadata-Version: 2.1
Name: layouts-segmentation-simplifier
Version: 0.0.2
Summary: Layout Segmentation Simplifier
Home-page: https://github.com/ponteineptique/lss
Author: Thibault Clérice
License: MIT
Platform: UNKNOWN
Classifier: License :: OSI Approved :: MIT License
Classifier: Programming Language :: Python
Classifier: Programming Language :: Python :: 3
Classifier: Programming Language :: Python :: 3.6
Classifier: Programming Language :: Python :: Implementation :: CPython
Classifier: Programming Language :: Python :: Implementation :: PyPy
Classifier: Topic :: Text Processing :: Linguistic
Requires-Python: >=3.7.0
Requires-Dist: lxml (==4.6.3)
Requires-Dist: simplification (==0.5.13)
Requires-Dist: shapely (<1.8.0,>=1.7.1)
Requires-Dist: Pillow (<8.4.0,>=8.3.2)
Requires-Dist: click (<9.0.0,>=8.0.1)
Requires-Dist: tqdm (<5.0.0,>=4.62.3)
